clonalEvolution/__init__.py
clonalEvolution/__main__.py
clonalEvolution/clonal_evolution_binned_loop.py
clonalEvolution/clonal_evolution_clone_matrix_loop.py
clonalEvolution/clonal_evolution_init.py
clonalEvolution/clonal_evolution_loop.py
clonalEvolution/external_plots.py
clonalEvolution/mainView.py
clonalEvolution/wmean.py
clonalEvolution-2.3.2.dist-info/LICENSE
clonalEvolution-2.3.2.dist-info/METADATA
clonalEvolution-2.3.2.dist-info/WHEEL
clonalEvolution-2.3.2.dist-info/entry_points.txt
clonalEvolution-2.3.2.dist-info/top_level.txt
clonalEvolution-2.3.2.dist-info/RECORD
